etherlens/__init__.py
etherlens/address_abi.py
etherlens/decoder.py
etherlens/observer.py
Etherlens-0.0.1.dist-info/LICENSE
Etherlens-0.0.1.dist-info/METADATA
Etherlens-0.0.1.dist-info/WHEEL
Etherlens-0.0.1.dist-info/top_level.txt
Etherlens-0.0.1.dist-info/RECORD
