Metadata-Version: 2.1
Name: Etherlens
Version: 0.0.1
Summary: EtherLens is a Python library designed to provide comprehensive insights into Ethereum transactions
Home-page: https://github.com/freemandaily/EtherLens
Author: freemandaily
Author-email: freemandaily <Onahchinemelem@gmail.com>
License: MIT License
Keywords: blockchain,ethereum,uniswap,decoder
Classifier: Development Status :: 4 - Beta
Classifier: Intended Audience :: Developers
Classifier: License :: OSI Approved :: MIT License
Classifier: Natural Language :: English
Classifier: Programming Language :: Python :: 3
Classifier: Programming Language :: Python :: 3.8
Classifier: Programming Language :: Python :: 3.9
Classifier: Programming Language :: Python :: 3.10
Classifier: Programming Language :: Python :: 3.11
Classifier: Operating System :: OS Independent
Requires-Python: >=3.8
License-File: LICENSE
Requires-Dist: web3 <7.0.0,>=6.0.0
Requires-Dist: uniswap-universal-router-decoder >=1.1.0
